py_animus/__init__.py
py_animus/file_io.py
py_animus/manifest_management.py
py_animus/py_animus.py
py_animus/utils.py
py_animus/helpers/__init__.py
py_animus/helpers/yaml_helper.py
py_animus-1.0.16.dist-info/LICENSE
py_animus-1.0.16.dist-info/METADATA
py_animus-1.0.16.dist-info/WHEEL
py_animus-1.0.16.dist-info/entry_points.txt
py_animus-1.0.16.dist-info/top_level.txt
py_animus-1.0.16.dist-info/RECORD
