Metadata-Version: 2.1
Name: py-animus
Version: 1.0.16
Summary: A python based plugable and extensible manifest processing system
Home-page: https://github.com/nicc777/py-animus
Author: Nico Coetzee
Author-email: nicc777@gmail.com
Project-URL: Bug Tracker, https://github.com/nicc777/py-animus/issues
Classifier: Programming Language :: Python :: 3
Classifier: License :: OSI Approved :: GNU General Public License v3 (GPLv3)
Classifier: Operating System :: OS Independent
Classifier: Intended Audience :: System Administrators
Classifier: Intended Audience :: Developers
Classifier: Development Status :: 4 - Beta
Classifier: Environment :: Console
Classifier: Environment :: Plugins
Classifier: Topic :: System :: Software Distribution
Classifier: Topic :: Utilities
Classifier: Topic :: Software Development
Classifier: Topic :: Software Development :: Libraries
Requires-Python: >=3.8
License-File: LICENSE
Requires-Dist: cerberus
Requires-Dist: PyYAML
Requires-Dist: chardet
